rcode/__init__.py
rcode/__main__.py
rcode/config.py
rcode/rcode.py
rcode_tddschn-0.5.2.dist-info/LICENSE
rcode_tddschn-0.5.2.dist-info/METADATA
rcode_tddschn-0.5.2.dist-info/WHEEL
rcode_tddschn-0.5.2.dist-info/entry_points.txt
rcode_tddschn-0.5.2.dist-info/RECORD
