Metadata-Version: 2.1
Name: rcode-tddschn
Version: 0.5.2
Summary: rcode Improved
Home-page: https://github.com/tddschn/rcode-tddschn
License: MIT
Keywords: vscode
Author: chvolkmann
Requires-Python: >=3.11,<3.12
Classifier: Environment :: Console
Classifier: Intended Audience :: Developers
Classifier: License :: OSI Approved :: MIT License
Classifier: Operating System :: OS Independent
Classifier: Programming Language :: Python :: 3
Classifier: Programming Language :: Python :: 3.11
Classifier: Topic :: Utilities
Requires-Dist: sshconf (>=0.2.5,<0.3.0)
Project-URL: Bug Tracker, https://github.com/tddschn/rcode-tddschn/issues
Project-URL: Repository, https://github.com/tddschn/rcode-tddschn
